py_pheno/__init__.py
py_pheno/func_preseason_api.cp38-win_amd64.pyd
py_pheno-0.0.26.dist-info/LICENSE
py_pheno-0.0.26.dist-info/METADATA
py_pheno-0.0.26.dist-info/WHEEL
py_pheno-0.0.26.dist-info/top_level.txt
py_pheno-0.0.26.dist-info/RECORD
