Metadata-Version: 2.1
Name: py-pheno
Version: 0.0.26
Summary: A small package for py_pheno analysis
Home-page: https://github.com/spjace/py_pheno
Author: Shen Pengju
Author-email: spjace@sina.com
Classifier: Programming Language :: Python :: 3
Classifier: License :: OSI Approved :: MIT License
Classifier: Operating System :: OS Independent
License-File: LICENSE
Requires-Dist: numpy
Requires-Dist: pandas
Requires-Dist: pingouin
Requires-Dist: scipy
